djangoldp_civilsociety/__init__.py
djangoldp_civilsociety/admin.py
djangoldp_civilsociety/apps.py
djangoldp_civilsociety/migrations/0001_initial.py
djangoldp_civilsociety/migrations/0002_add_timestamps_to_models.py
djangoldp_civilsociety/migrations/__init__.py
djangoldp_civilsociety/models/__init__.py
djangoldp_civilsociety/models/object.py
djangoldp_civilsociety/models/type.py
djangoldp_civilsociety/models/zzz_signals.py
djangoldp_factchecking/__init__.py
djangoldp_factchecking/admin.py
djangoldp_factchecking/apps.py
djangoldp_factchecking/migrations/0001_initial.py
djangoldp_factchecking/migrations/0002_add_timestamps_to_models.py
djangoldp_factchecking/migrations/__init__.py
djangoldp_factchecking/models/__init__.py
djangoldp_factchecking/models/affiliation.py
djangoldp_factchecking/models/object.py
djangoldp_factchecking/models/topic.py
djangoldp_factchecking/models/zzz_signals.py
djangoldp_interactiveinfographic/__init__.py
djangoldp_interactiveinfographic/admin.py
djangoldp_interactiveinfographic/apps.py
djangoldp_interactiveinfographic/migrations/0001_initial.py
djangoldp_interactiveinfographic/migrations/0002_add_timestamps_to_models.py
djangoldp_interactiveinfographic/migrations/__init__.py
djangoldp_interactiveinfographic/models/__init__.py
djangoldp_interactiveinfographic/models/object.py
djangoldp_interactiveinfographic/models/zzz_signals.py
djangoldp_mediaobject/__init__.py
djangoldp_mediaobject/admin.py
djangoldp_mediaobject/apps.py
djangoldp_mediaobject/migrations/0001_initial.py
djangoldp_mediaobject/migrations/0002_add_timestamps_to_models.py
djangoldp_mediaobject/migrations/__init__.py
djangoldp_mediaobject/models/__base_object.py
djangoldp_mediaobject/models/__init__.py
djangoldp_mediaobject/models/asset.py
djangoldp_mediaobject/models/category.py
djangoldp_mediaobject/models/format.py
djangoldp_mediaobject/models/keyword.py
djangoldp_mediaobject/models/language.py
djangoldp_mediaobject/models/zzz_signals.py
djangoldp_object3d/__init__.py
djangoldp_tems-3.0.1.dist-info/METADATA
djangoldp_tems-3.0.1.dist-info/WHEEL
djangoldp_tems-3.0.1.dist-info/top_level.txt
djangoldp_tems-3.0.1.dist-info/RECORD
