Metadata-Version: 2.4
Name: djangoldp_tems
Version: 3.0.1
Summary: djangoldp package for TEMS
Home-page: https://git.startinblox.com/djangoldp-packages/djangoldp-tems
Author: Startin'blox
Author-email: jbaptiste@startinblox.com
License: MIT
Classifier: Programming Language :: Python :: 3
Requires-Dist: djangoldp~=5.0.0
Requires-Dist: djangoldp_account~=5.0.0
Requires-Dist: djangoldp_edc~=1.0.0
Provides-Extra: include-package-data
Requires-Dist: True; extra == "include-package-data"
Provides-Extra: dev
Requires-Dist: factory_boy>=2.11.0; extra == "dev"
